poem_plugins/__init__.py
poem_plugins/config/__init__.py
poem_plugins/config/base.py
poem_plugins/config/git.py
poem_plugins/dispatchers/__init__.py
poem_plugins/dispatchers/base.py
poem_plugins/dispatchers/version.py
poem_plugins/general/__init__.py
poem_plugins/general/strenum.py
poem_plugins/general/version/__init__.py
poem_plugins/general/version/drivers/__init__.py
poem_plugins/general/version/drivers/git.py
poem_plugins/handlers/__init__.py
poem_plugins/handlers/version.py
poem_plugins/plugins/__init__.py
poem_plugins/plugins/base.py
poem_plugins/plugins/version.py
poem_plugins-1.2.0.dist-info/LICENSE
poem_plugins-1.2.0.dist-info/METADATA
poem_plugins-1.2.0.dist-info/WHEEL
poem_plugins-1.2.0.dist-info/entry_points.txt
poem_plugins-1.2.0.dist-info/RECORD
