Metadata-Version: 2.1
Name: poem-plugins
Version: 1.2.0
Summary: Some set of poetry plugins
Home-page: https://pypi.org/project/poem-plugins
License: MIT
Keywords: plugins,poetry,packaging
Author: Ivan Sitkin
Author-email: alvinera@yandex.ru
Requires-Python: >=3.9,<4.0
Classifier: Development Status :: 5 - Production/Stable
Classifier: Environment :: Console
Classifier: Intended Audience :: Developers
Classifier: Intended Audience :: Education
Classifier: Intended Audience :: Information Technology
Classifier: Intended Audience :: System Administrators
Classifier: License :: OSI Approved :: MIT License
Classifier: Operating System :: MacOS :: MacOS X
Classifier: Operating System :: Microsoft :: Windows
Classifier: Operating System :: POSIX
Classifier: Operating System :: POSIX :: Linux
Classifier: Programming Language :: Python
Classifier: Programming Language :: Python :: 3
Classifier: Programming Language :: Python :: 3.9
Classifier: Programming Language :: Python :: 3.10
Classifier: Programming Language :: Python :: 3.11
Classifier: Programming Language :: Python :: 3.12
Classifier: Programming Language :: Python :: 3 :: Only
Classifier: Programming Language :: Python :: 3.13
Classifier: Topic :: Software Development :: Build Tools
Classifier: Topic :: Software Development :: Libraries :: Python Modules
Requires-Dist: poetry (>=1.5.0,<3.0.0)
Project-URL: Documentation, https://github.com/alviner/poem-plugins
Project-URL: Repository, https://github.com/alviner/poem-plugins
